{
    "name": "Kathmandu Codes",
    "establishedAt": 1534982400,
    "location": "Lazimpat, Kathmandu",
    "website": "https://kathmandu.codes/",
    "email": "ktmcodes@gmail.com",
    "phone": "+977-9801155685",
    "socials": {
      "facebook": "https://www.facebook.com/kathmandu.codes/",
      "github": "https://github.com/kathmanducodes/",
      "instagram": "https://instagram.com/kathmandu.codes/",
      "linkedin": "https://www.linkedin.com/company/kathmanducodes/",
      "twitter": null,
      "youtube": null
    }
  }
